{
  "description": "Pipeline for parsing panw traffic logs. Requires the geoip and user_agent plugins.",
  "processors": [{
    "grok": {
      "field": "message",
      "patterns":[
        "\"?%{IP_LIST:panw.traffic.remote_ip_list} - %{DATA:panw.traffic.user_name} \\[%{HTTPDATE:panw.traffic.time}\\] \"%{GREEDYDATA:panw.traffic.info}\" %{NUMBER:panw.traffic.response_code} %{NUMBER:panw.traffic.body_sent.bytes} \"%{DATA:panw.traffic.referrer}\" \"%{DATA:panw.traffic.agent}\""
        ],
      "pattern_definitions": {
        "IP_LIST": "%{IP}(\"?,?\\s*%{IP})*"
      },
      "ignore_missing": true
    }
  }, {
    "grok": {
      "field": "panw.traffic.info",
      "patterns": [
          "%{WORD:panw.traffic.method} %{DATA:panw.traffic.url} HTTP/%{NUMBER:panw.traffic.http_version}",
          ""
      ],
      "ignore_missing": true
    }
  }, {
    "remove": {
      "field": "panw.traffic.info"
    }
  }, {
    "split": {
      "field": "panw.traffic.remote_ip_list",
      "separator": "\"?,?\\s+"
    }
  }, {
    "script": {
      "lang": "painless",
      "inline": "boolean isPrivate(def ip) { try { StringTokenizer tok = new StringTokenizer(ip, '.'); int firstByte = Integer.parseInt(tok.nextToken());       int secondByte = Integer.parseInt(tok.nextToken());       if (firstByte == 10) {         return true;       }       if (firstByte == 192 && secondByte == 168) {         return true;       }       if (firstByte == 172 && secondByte >= 16 && secondByte <= 31) {         return true;       }       if (firstByte == 127) {         return true;       }       return false;     } catch (Exception e) {       return false;     }   }   def found = false;   for (def item : ctx.panw.traffic.remote_ip_list) {     if (!isPrivate(item)) {       ctx.panw.traffic.remote_ip = item;       found = true;       break;     }   }   if (!found) {     ctx.panw.traffic.remote_ip = ctx.panw.traffic.remote_ip_list[0];   }"
      }
  }, {
    "remove":{
      "field": "message"
    }
  }, {
    "rename": {
      "field": "@timestamp",
      "target_field": "read_timestamp"
    }
  }, {
    "date": {
      "field": "panw.traffic.time",
      "target_field": "@timestamp",
      "formats": ["dd/MMM/YYYY:H:m:s Z"]
    }
  }, {
    "remove": {
      "field": "panw.traffic.time"
    }
  }, {
    "user_agent": {
      "field": "panw.traffic.agent",
      "target_field": "panw.traffic.user_agent"
    }
  }, {
    "remove": {
      "field": "panw.traffic.agent"
    }
  }, {
    "geoip": {
      "field": "panw.traffic.remote_ip",
      "target_field": "panw.traffic.geoip"
    }
  }],
  "on_failure" : [{
    "set" : {
      "field" : "error.message",
      "value" : "{{ _ingest.on_failure_message }}"
    }
  }]
}
